{
  "nav": [
    {
      "label": "Klachten",
      "href": "/klachten",
      "children": [
        { "label": "Kaakpijn", "href": "/klachten/kaakpijn" },
        { "label": "Hoofdpijn & Migraine", "href": "/klachten/hoofdpijn-migraine" },
        { "label": "Tinnitus", "href": "/klachten/tinnitus" },
        { "label": "Zenuwpijn", "href": "/klachten/zenuwpijn" },
        { "label": "Tandenknarsen", "href": "/klachten/tandenknarsen" },
        { "label": "Stijve Nek", "href": "/klachten/stijve-nek" },
        { "label": "Rug- & Nekklachten", "href": "/klachten/rug-nekklachten" },
        { "label": "Apneu & Snurken", "href": "/klachten/apneu-snurken" },
        { "label": "Malocclusie", "href": "/klachten/malocclusie" }
      ]
    },
    { "label": "Diagnostiek", "href": "/diagnostiek" },
    { "label": "Behandeling", "href": "/behandeling" },
    { "label": "Over Ons", "href": "/over-ons" },
    { "label": "FAQ", "href": "/faq" },
    { "label": "Kennisbank", "href": "/kennisbank" }
  ],
  "cta": "Boek Gratis Scan",
  "footer": {
    "description": "Vincor (Vinculum Corporis — de band van het lichaam). Gespecialiseerd in occlusie & houdingsdiagnostiek.",
    "klachtenTitle": "Klachten",
    "behandelingTitle": "Behandeling",
    "contactTitle": "Contact",
    "behandelingLinks": [
      { "label": "Fase 1 — Relaxatiesplint", "href": "/behandeling/fase-1-relaxatiesplint" },
      { "label": "Fase 2 — Repositioneringssplint", "href": "/behandeling/fase-2-repositioneringssplint" },
      { "label": "Fase 3 — Reconstructie", "href": "/behandeling/fase-3-reconstructie" }
    ],
    "privacy": "Privacy",
    "terms": "Voorwaarden",
    "cookieSettings": "Cookievoorkeuren"
  },
  "cookie": {
    "title": "Wij respecteren uw privacy",
    "description": "Wij gebruiken alleen strikt noodzakelijke cookies. Voor statistieken en de kaart van onze locatie vragen wij uw toestemming. U kunt uw keuze later altijd wijzigen via 'Cookievoorkeuren' in de footer.",
    "acceptAll": "Alles accepteren",
    "rejectAll": "Alleen essentieel",
    "customize": "Aanpassen",
    "save": "Voorkeuren opslaan",
    "essential": {
      "label": "Essentieel (altijd aan)",
      "description": "Nodig voor basisfunctionaliteit zoals het onthouden van uw cookievoorkeuren."
    },
    "analytics": {
      "label": "Statistieken",
      "description": "Cloudflare Web Analytics — anonieme bezoekersstatistieken zonder persoonlijke profilering."
    },
    "maps": {
      "label": "Google Maps",
      "description": "Tonen van onze praktijklocatie via Google Maps. Google plaatst daarbij cookies."
    }
  }
}
